[
    {
        "url": "https://www.eldorado.ru//cat/detail/sistemnyy-fotoapparat-panasonic-lumix-gh5s-dc-gh5see-k/",
        "author": "Илья",
        "date": "21.10.2019 23:14:53",
        "content": "Прикольный фотоаппарат. Мне понравилась светочувствительность и фокус. Вне зависимости, какой по отдаленности объект я снимаю, он его улавливает. Тут даже есть возможность записи запись в 4К и С4К! Мечта для фотографа. Ключевой особенностью аппарата считаю двойной нативный ISO, отчего шумность минимальная. Сенсор Live MOS тоже на уровне, благодаря ему переключаю ISO на максимум. Я получаю ту глубину из расфокусировки, которую ожидаю, поэтому постобработка фото не обязательна. Они и так получаются суперкрасивыми. Серийная съемка здесь производится на 8 к/с, а если объект статичен, тогда на 12 к/с. и способности удерживать непрерывный автофокус. В таком режиме он может производить серийную съемку до 8 кадров в секунду, а при фокусировке на статичном объекте — до 12. Увеличивая (20х) MF, получается даже запечатлеть звездное небо, луну. Потрясающе!                    0 человек считают этот отзыв полезным"
    },
    {
        "url": "https://www.eldorado.ru//cat/detail/sistemnyy-fotoapparat-panasonic-lumix-gh5s-dc-gh5see-k/",
        "author": "Костя",
        "date": "21.11.2019 15:17:59",
        "content": "Взял фотоаппарат уже давно, в основном использую его для видеосъемки. снимаю красивых девушек на улице и в студии, как бонус к фотосессии. Резкость видео поражает. Особенно эффектно смотрится замедленная съемка. за счет стабилизатора картинка не шатается. В сумерках настраиваю светочувствительность на максимум, но шумов все равно нет. Цвета глубокие и мягкие. Автофокус самый быстрый из всех что я видел, при чем даже без света улавливает объект. Я не вижу конкурентов для этой камеры вообще.                    2 человека считают этот отзыв полезным"
    }
]