[
    {
        "url": "https://www.eldorado.ru//cat/detail/stojka-dlja-tv-akma-v3-2052-black/",
        "author": "Владимир",
        "date": "29.05.2014 07:54:23",
        "content": "Качественная стойка, собирается быстро. Единственная проблема кронштейн(на котором держится сам телевизор)  крепится к стойке всего к одной полке (в виде трапеции), хотя полок две.                    28 человек считают этот отзыв полезным"
    },
    {
        "url": "https://www.eldorado.ru//cat/detail/stojka-dlja-tv-akma-v3-2052-black/",
        "author": "Ольга",
        "date": "30.10.2013 20:47:03",
        "content": "Хорошая стойка, по дизайну нравиться и надежная.                    29 человек считают этот отзыв полезным"
    },
    {
        "url": "https://www.eldorado.ru//cat/detail/stojka-dlja-tv-akma-v3-2052-black/",
        "author": "Олег",
        "date": "12.01.2014 11:26:49",
        "content": "Отличная стойка.Купил на днях 40см.ширина то что надо вписалась класно доволен.Даже жена довольна не ворчит.Дизайн шикарный спасибо тому кто ее спроектировал.                    22 человека считают этот отзыв полезным"
    },
    {
        "url": "https://www.eldorado.ru//cat/detail/stojka-dlja-tv-akma-v3-2052-black/",
        "author": "Виктор",
        "date": "06.05.2014 09:59:18",
        "content": "Стойка на 5+, дизайн шикарный, сборка несложная. Семья довольна. Кстати на фото смотрится хуже.                    13 человек считают этот отзыв полезным"
    },
    {
        "url": "https://www.eldorado.ru//cat/detail/stojka-dlja-tv-akma-v3-2052-black/",
        "author": "Артем",
        "date": "19.06.2017 23:19:42",
        "content": "Хорошая полка.\r\n- За то, что кронштейн на котором держится сам телевизор крепится к стойке всего к одной полке  хотя полок две. Можно и так конечно оставить. Но я просверлил два отверстия и закрепил на 4 болта                    6 человек считают этот отзыв полезным"
    },
    {
        "url": "https://www.eldorado.ru//cat/detail/stojka-dlja-tv-akma-v3-2052-black/",
        "author": "Елена",
        "date": "29.12.2019 19:55:16",
        "content": "Слов цензурных нет! В комплекте должны были быть 4 гайки с шайбами. Их не было!!! \r\nКороткие шпильки, которые проходят внутри труб ножек, как минимум на 25 мм меньше, чем требуется. Закрепить невозможно! \r\nЖелание поддерживать отечественного производителя отпало напрочь.  Уже китайцы лучше делают, чем наши. По крайней мере, крепеж кладут не жалеют.                    2 человека считают этот отзыв полезным"
    },
    {
        "url": "https://www.eldorado.ru//cat/detail/stojka-dlja-tv-akma-v3-2052-black/",
        "author": "Валерия",
        "date": "23.04.2021 11:09:07",
        "content": "Стойка вроде неплохая, но не супер. \r\nСмотрится да красиво, неплохо так. \r\nНо ее конструкций вызывает сомнения в надежности... Как ни прикручивай шпильки - телевизор весом 12 кг все равно наклоняет центральную стойку - такое ощущение, что конструкций может переломаться.. А заявлен вес аж 60 кг - смешно...\r\nИнструкция вообще бред, надейтесь только на свой разум, по инструкции не собрать. Все надо додумывать самому.                    1 человек считает этот отзыв полезным"
    },
    {
        "url": "https://www.eldorado.ru//cat/detail/stojka-dlja-tv-akma-v3-2052-black/",
        "author": "Татьяна",
        "date": "12.01.2016 20:52:05",
        "content": "Отличная стойка, смотрится очень аккуратно и компактно особенно для телевизора размер которого 140 см.очень довольна.                    5 человек считают этот отзыв полезным"
    },
    {
        "url": "https://www.eldorado.ru//cat/detail/stojka-dlja-tv-akma-v3-2052-black/",
        "author": "Елена",
        "date": "21.09.2020 09:37:36",
        "content": "Красивая,стильная стойка под телевизор. Легкая,гармонично вписалась в интерьер. Нам понравилась!                    0 человек считают этот отзыв полезным"
    },
    {
        "url": "https://www.eldorado.ru//cat/detail/stojka-dlja-tv-akma-v3-2052-black/",
        "author": "Юрий",
        "date": "25.02.2021 14:45:37",
        "content": "Стойка удобна в том, что можно поставить в любой угол, не надо ничего сверлить. Нужно более подробную инструкцию сборки .                    0 человек считают этот отзыв полезным"
    }
]