[
    {
        "url": "https://www.eldorado.ru//cat/detail/tumba-dlya-tv-akma-v3-1511-silver/",
        "author": "Юлия",
        "date": "01.10.2019 23:38:35",
        "content": "Стойку эту покупали в новую квартиру когда переезжали. Брали ее потому что по цвету нам подходит, и выглядит симпатично она. В итоге не прогадали с ней, очень удобная и практичная оказалась. Телевизор, колонки отлично поместились на ней и без проблем. Удобно, что взади у нее есть дырочки, можно провода аккуратно убрать, чтобы не валялись по комнате. Это нам прям больше всего понравилось. Да и удобно, что можно много чего еще поставить на нее. Пыль вытирать тоже не составляет проблем, быстро все протирается и еще долго потом не скапливается.                    0 человек считают этот отзыв полезным"
    },
    {
        "url": "https://www.eldorado.ru//cat/detail/tumba-dlya-tv-akma-v3-1511-silver/",
        "author": "Мария",
        "date": "10.10.2019 21:37:23",
        "content": "Мы с парнем купили эту стойку, когда купили себе игровую приставку. На нашей старой тумбочке уже места не было ни для чего, все захламлено было…(( Поэтому решили обновить. Очень нам этот вариант понравился – и цена, и цвет, и как она оформлена. Отлично подошла. Теперь все аккуратно лежит и на своих местах, нет бардака )) Да и ухаживать за ней легко, ничего специального делать не нужно. Стоит прочно на полу, поэтому телевизор не шатается на ней. Мы очень довольны что купили ее, прям очень красиво теперь выглядит всё в комнате)                    0 человек считают этот отзыв полезным"
    }
]